script.py
keyo/__init__.py
keyo/app.py
keyo/sanic_class.py
keyo/script.py
keyo/sdk_functions.py
keyo_coral-0.3.1.dist-info/METADATA
keyo_coral-0.3.1.dist-info/WHEEL
keyo_coral-0.3.1.dist-info/entry_points.txt
keyo_coral-0.3.1.dist-info/top_level.txt
keyo_coral-0.3.1.dist-info/RECORD
