Metadata-Version: 2.1
Name: keyo-coral
Version: 0.3.1
Summary: SDK sanic application
Author: swalih
Author-email: <swalihchungath@gmail.com>
Keywords: sanic,palm
Classifier: Development Status :: 1 - Planning
Classifier: Intended Audience :: Developers
Classifier: Programming Language :: Python :: 3
Classifier: Operating System :: Unix
Classifier: Operating System :: MacOS :: MacOS X
Classifier: Operating System :: Microsoft :: Windows
Requires-Dist: sanic
